{"chunk_definitions":[{"chunk_id":"cbgc7mswis3m4","chunk_label":"unnamed-chunk-1","document_id":null,"expansion_state":1,"options":[],"row":11,"row_count":1,"visible":true},{"chunk_id":"cb80jym8mbmnm","chunk_label":"unnamed-chunk-2","document_id":null,"expansion_state":1,"options":[],"row":17,"row_count":1,"visible":true},{"chunk_id":"c8nt77izmt035","chunk_label":"unnamed-chunk-3","document_id":null,"expansion_state":1,"options":[],"row":24,"row_count":1,"visible":true},{"chunk_id":"cbhnl0z642ouc","chunk_label":"unnamed-chunk-4","document_id":null,"expansion_state":1,"options":[],"row":33,"row_count":1,"visible":true},{"chunk_id":"c58s7eirrpbxz","chunk_label":"unnamed-chunk-5","document_id":null,"expansion_state":1,"options":[],"row":42,"row_count":1,"visible":true},{"chunk_id":"cm80b9hbjziia","chunk_label":"unnamed-chunk-6","document_id":null,"expansion_state":1,"options":[],"row":57,"row_count":1,"visible":true},{"chunk_id":"cjybcorw0cp93","chunk_label":"unnamed-chunk-7","document_id":null,"expansion_state":1,"options":[],"row":65,"row_count":1,"visible":true},{"chunk_id":"cirajq09l886r","chunk_label":"unnamed-chunk-8","document_id":null,"expansion_state":1,"options":[],"row":83,"row_count":1,"visible":true}],"doc_write_time":1537843939}